easyx/__init__.py
easyx/easyX.py
easyx-1.1.0.dist-info/LICENSE
easyx-1.1.0.dist-info/METADATA
easyx-1.1.0.dist-info/WHEEL
easyx-1.1.0.dist-info/top_level.txt
easyx-1.1.0.dist-info/RECORD
