Metadata-Version: 2.1
Name: easyx
Version: 1.1.0
Summary: A library for storing big data
Home-page: https://github.com/myousefnezhad/easyx
Author: Tony (Muhammad) Yousefnezhad
Author-email: <myousefnezhad@gmail.com>
Keywords: python,big data,HDF5,data storage,nonhomogeneous data structure
Classifier: Intended Audience :: Developers
Classifier: Programming Language :: Python :: 3
Classifier: Operating System :: Unix
Classifier: Operating System :: MacOS :: MacOS X
Classifier: Operating System :: Microsoft :: Windows
License-File: LICENSE
Requires-Dist: numpy
Requires-Dist: h5py
